README.md
setup.cfg
setup.py
pyyolo/__init__.py
pyyolo/cyolo.py
pyyolo/yolo.py
pyyolo.egg-info/PKG-INFO
pyyolo.egg-info/SOURCES.txt
pyyolo.egg-info/dependency_links.txt
pyyolo.egg-info/requires.txt
pyyolo.egg-info/top_level.txt