Metadata-Version: 2.1
Name: pyyolo
Version: 0.1.5
Summary: Easy to use Python wrapper for YOLO Real-Time ObjectDetection Library
Home-page: https://github.com/goktug97/PyYOLO
Author: Göktuğ Karakaşlı
Author-email: karakasligk@gmail.com
License: MIT
Download-URL: https://github.com/goktug97/PyYOLO/archive/v0.1.4.tar.gz
Platform: UNKNOWN
Classifier: Programming Language :: Python :: 3
Classifier: License :: OSI Approved :: MIT License
Classifier: Operating System :: POSIX :: Linux
Requires-Python: >=3.6
